GuiguJinshuQuan5ce/Dockerfile
GuiguJinshuQuan5ce/README.md
GuiguJinshuQuan5ce/__init__.py
GuiguJinshuQuan5ce/__main__.py
GuiguJinshuQuan5ce/file.epub
GuiguJinshuQuan5ce/index.html
GuiguJinshuQuan5ce/css/__init__.py
GuiguJinshuQuan5ce/css/annotations.css
GuiguJinshuQuan5ce/css/main.css
GuiguJinshuQuan5ce/css/normalize.css
GuiguJinshuQuan5ce/css/popup.css
GuiguJinshuQuan5ce/font/__init__.py
GuiguJinshuQuan5ce/font/fontello.eot
GuiguJinshuQuan5ce/font/fontello.svg
GuiguJinshuQuan5ce/font/fontello.ttf
GuiguJinshuQuan5ce/font/fontello.woff
GuiguJinshuQuan5ce/img/__init__.py
GuiguJinshuQuan5ce/img/annotator-glyph-sprite.png
GuiguJinshuQuan5ce/img/annotator-icon-sprite.png
GuiguJinshuQuan5ce/img/apple-touch-icon.png
GuiguJinshuQuan5ce/img/cancelfullscreen.png
GuiguJinshuQuan5ce/img/close.png
GuiguJinshuQuan5ce/img/fullscreen.png
GuiguJinshuQuan5ce/img/loader.gif
GuiguJinshuQuan5ce/img/menu-icon.png
GuiguJinshuQuan5ce/img/save.png
GuiguJinshuQuan5ce/img/saved.png
GuiguJinshuQuan5ce/img/settings-s.png
GuiguJinshuQuan5ce/img/settings.png
GuiguJinshuQuan5ce/img/star.png
GuiguJinshuQuan5ce/js/__init__.py
GuiguJinshuQuan5ce/js/epub.js
GuiguJinshuQuan5ce/js/epub.min.js
GuiguJinshuQuan5ce/js/epub.min.map
GuiguJinshuQuan5ce/js/hooks.min.js
GuiguJinshuQuan5ce/js/hooks.min.map
GuiguJinshuQuan5ce/js/reader.js
GuiguJinshuQuan5ce/js/reader.js.map
GuiguJinshuQuan5ce/js/reader.min.js
GuiguJinshuQuan5ce/js/reader.min.map
GuiguJinshuQuan5ce/js/hooks/__init__.py
GuiguJinshuQuan5ce/js/hooks/extensions/__init__.py
GuiguJinshuQuan5ce/js/hooks/extensions/highlight.js
GuiguJinshuQuan5ce/js/libs/__init__.py
GuiguJinshuQuan5ce/js/libs/jquery.min.js
GuiguJinshuQuan5ce/js/libs/localforage.min.js
GuiguJinshuQuan5ce/js/libs/screenfull.js
GuiguJinshuQuan5ce/js/libs/screenfull.min.js
GuiguJinshuQuan5ce/js/libs/zip.min.js
GuiguJinshuQuan5ce/js/plugins/__init__.py
GuiguJinshuQuan5ce/js/plugins/hypothesis.js
GuiguJinshuQuan5ce/js/plugins/search.js
guigu_jinshu_quan5ce-2022.10.6.0.dist-info/METADATA
guigu_jinshu_quan5ce-2022.10.6.0.dist-info/WHEEL
guigu_jinshu_quan5ce-2022.10.6.0.dist-info/entry_points.txt
guigu_jinshu_quan5ce-2022.10.6.0.dist-info/top_level.txt
guigu_jinshu_quan5ce-2022.10.6.0.dist-info/RECORD
